coloramas/__init__.py
coloramas/coloramas_file.py
coloramas-0.23.dist-info/METADATA
coloramas-0.23.dist-info/WHEEL
coloramas-0.23.dist-info/top_level.txt
coloramas-0.23.dist-info/RECORD
